<theme>
	<formatVersion>7</formatVersion>
	<include>./../theme.xml</include>

		<view name="system, basic, detailed, video, grid, gamecarousel">
			<image name="logo">
				<path>./_inc/system.png</path>
			</image>
			
		<text name="TextDescLong" extra="true">
				<text>Pokémon is a Japanese media franchise managed by The Pokémon Company, a company founded by Nintendo, Game Freak, and Creatures. The franchise was created by Satoshi Tajiri in 1996, and is centered on fictional creatures called "Pokémon". In Pokémon, humans, known as Pokémon Trainers, catch and train Pokémon to battle other Pokémon for sport. All media works within the franchise are set in the Pokémon universe. The English slogan for the franchise is "Gotta Catch ‘Em All!".</text>
		</text>

		<text name="TextDescShort" extra="true">
				<text>Pokémon is a Japanese media franchise managed by The Pokémon Company.</text>
		</text>
		
		<text name="TextDescName" extra="true">
				<text>Pokémon</text>
		</text>

		<text name="TextDescCategory" extra="true">
				<text>Collection</text>
		</text>	

		<text name="TextDescYear" extra="true">
				<text>1996</text>
		</text>			
		
	</view>	
	
</theme>